thonny_microbit-0.3.dist-info/METADATA
thonny_microbit-0.3.dist-info/RECORD
thonny_microbit-0.3.dist-info/WHEEL
thonny_microbit-0.3.dist-info/top_level.txt
thonnycontrib/microbit/__init__.py
thonnycontrib/microbit/api_stubs/antigravity.py
thonnycontrib/microbit/api_stubs/array.py
thonnycontrib/microbit/api_stubs/audio.py
thonnycontrib/microbit/api_stubs/builtins.py
thonnycontrib/microbit/api_stubs/collections.py
thonnycontrib/microbit/api_stubs/gc.py
thonnycontrib/microbit/api_stubs/love.py
thonnycontrib/microbit/api_stubs/machine.py
thonnycontrib/microbit/api_stubs/math.py
thonnycontrib/microbit/api_stubs/microbit.py
thonnycontrib/microbit/api_stubs/micropython.py
thonnycontrib/microbit/api_stubs/music.py
thonnycontrib/microbit/api_stubs/neopixel.py
thonnycontrib/microbit/api_stubs/os.py
thonnycontrib/microbit/api_stubs/radio.py
thonnycontrib/microbit/api_stubs/random.py
thonnycontrib/microbit/api_stubs/speech.py
thonnycontrib/microbit/api_stubs/struct.py
thonnycontrib/microbit/api_stubs/sys.py
thonnycontrib/microbit/api_stubs/this.py
thonnycontrib/microbit/api_stubs/time.py
thonnycontrib/microbit/api_stubs/ucollections.py
thonnycontrib/microbit/api_stubs/ustruct.py
thonnycontrib/microbit/api_stubs/utime.py
thonnycontrib/microbit/firmware/microbit-micropython-v1.0.1.hex
thonnycontrib/microbit/res/run.flash_microbit.gif
